sentwits/__init__.py
sentwits/sentwits.py
Sentwits-0.0.3.dist-info/LICENSE.txt
Sentwits-0.0.3.dist-info/METADATA
Sentwits-0.0.3.dist-info/WHEEL
Sentwits-0.0.3.dist-info/top_level.txt
Sentwits-0.0.3.dist-info/RECORD
